README.rst
setup.py
mypackage_bod/__init__.py
mypackage_bod/module1.py
mypackage_bod/module2.py
mypackage_bod.egg-info/PKG-INFO
mypackage_bod.egg-info/SOURCES.txt
mypackage_bod.egg-info/dependency_links.txt
mypackage_bod.egg-info/top_level.txt