Metadata-Version: 1.0
Name: mypackage-bod
Version: 0.0.1
Summary: a pip-installable package example
Home-page: https://github.com/foxyolegus
Author: Oleg Barzasekov
Author-email: oleg.barzasekov@gmail.com
License: MIT
Keywords: example
Platform: UNKNOWN
